{
    "images": [
        {
            "high_idx": 0,
            "image_name": "000000000.png",
            "low_idx": 0
        },
        {
            "high_idx": 0,
            "image_name": "000000001.png",
            "low_idx": 0
        },
        {
            "high_idx": 0,
            "image_name": "000000002.png",
            "low_idx": 0
        },
        {
            "high_idx": 0,
            "image_name": "000000003.png",
            "low_idx": 0
        },
        {
            "high_idx": 0,
            "image_name": "000000004.png",
            "low_idx": 0
        },
        {
            "high_idx": 0,
            "image_name": "000000005.png",
            "low_idx": 0
        },
        {
            "high_idx": 0,
            "image_name": "000000006.png",
            "low_idx": 0
        },
        {
            "high_idx": 0,
            "image_name": "000000007.png",
            "low_idx": 0
        },
        {
            "high_idx": 0,
            "image_name": "000000008.png",
            "low_idx": 0
        },
        {
            "high_idx": 0,
            "image_name": "000000009.png",
            "low_idx": 0
        },
        {
            "high_idx": 0,
            "image_name": "000000010.png",
            "low_idx": 0
        },
        {
            "high_idx": 0,
            "image_name": "000000011.png",
            "low_idx": 1
        },
        {
            "high_idx": 0,
            "image_name": "000000012.png",
            "low_idx": 1
        },
        {
            "high_idx": 0,
            "image_name": "000000013.png",
            "low_idx": 1
        },
        {
            "high_idx": 0,
            "image_name": "000000014.png",
            "low_idx": 1
        },
        {
            "high_idx": 0,
            "image_name": "000000015.png",
            "low_idx": 1
        },
        {
            "high_idx": 0,
            "image_name": "000000016.png",
            "low_idx": 1
        },
        {
            "high_idx": 0,
            "image_name": "000000017.png",
            "low_idx": 1
        },
        {
            "high_idx": 0,
            "image_name": "000000018.png",
            "low_idx": 1
        },
        {
            "high_idx": 0,
            "image_name": "000000019.png",
            "low_idx": 1
        },
        {
            "high_idx": 0,
            "image_name": "000000020.png",
            "low_idx": 1
        },
        {
            "high_idx": 0,
            "image_name": "000000021.png",
            "low_idx": 1
        },
        {
            "high_idx": 0,
            "image_name": "000000022.png",
            "low_idx": 2
        },
        {
            "high_idx": 0,
            "image_name": "000000023.png",
            "low_idx": 2
        },
        {
            "high_idx": 0,
            "image_name": "000000024.png",
            "low_idx": 3
        },
        {
            "high_idx": 0,
            "image_name": "000000025.png",
            "low_idx": 3
        },
        {
            "high_idx": 0,
            "image_name": "000000026.png",
            "low_idx": 4
        },
        {
            "high_idx": 0,
            "image_name": "000000027.png",
            "low_idx": 4
        },
        {
            "high_idx": 0,
            "image_name": "000000028.png",
            "low_idx": 5
        },
        {
            "high_idx": 0,
            "image_name": "000000029.png",
            "low_idx": 5
        },
        {
            "high_idx": 0,
            "image_name": "000000030.png",
            "low_idx": 6
        },
        {
            "high_idx": 0,
            "image_name": "000000031.png",
            "low_idx": 6
        },
        {
            "high_idx": 0,
            "image_name": "000000032.png",
            "low_idx": 7
        },
        {
            "high_idx": 0,
            "image_name": "000000033.png",
            "low_idx": 7
        },
        {
            "high_idx": 0,
            "image_name": "000000034.png",
            "low_idx": 8
        },
        {
            "high_idx": 0,
            "image_name": "000000035.png",
            "low_idx": 8
        },
        {
            "high_idx": 0,
            "image_name": "000000036.png",
            "low_idx": 9
        },
        {
            "high_idx": 0,
            "image_name": "000000037.png",
            "low_idx": 9
        },
        {
            "high_idx": 0,
            "image_name": "000000038.png",
            "low_idx": 10
        },
        {
            "high_idx": 0,
            "image_name": "000000039.png",
            "low_idx": 10
        },
        {
            "high_idx": 0,
            "image_name": "000000040.png",
            "low_idx": 11
        },
        {
            "high_idx": 0,
            "image_name": "000000041.png",
            "low_idx": 11
        },
        {
            "high_idx": 0,
            "image_name": "000000042.png",
            "low_idx": 12
        },
        {
            "high_idx": 0,
            "image_name": "000000043.png",
            "low_idx": 12
        },
        {
            "high_idx": 0,
            "image_name": "000000044.png",
            "low_idx": 12
        },
        {
            "high_idx": 0,
            "image_name": "000000045.png",
            "low_idx": 12
        },
        {
            "high_idx": 0,
            "image_name": "000000046.png",
            "low_idx": 12
        },
        {
            "high_idx": 0,
            "image_name": "000000047.png",
            "low_idx": 12
        },
        {
            "high_idx": 0,
            "image_name": "000000048.png",
            "low_idx": 12
        },
        {
            "high_idx": 0,
            "image_name": "000000049.png",
            "low_idx": 12
        },
        {
            "high_idx": 0,
            "image_name": "000000050.png",
            "low_idx": 12
        },
        {
            "high_idx": 0,
            "image_name": "000000051.png",
            "low_idx": 12
        },
        {
            "high_idx": 0,
            "image_name": "000000052.png",
            "low_idx": 12
        },
        {
            "high_idx": 0,
            "image_name": "000000053.png",
            "low_idx": 13
        },
        {
            "high_idx": 0,
            "image_name": "000000054.png",
            "low_idx": 13
        },
        {
            "high_idx": 0,
            "image_name": "000000055.png",
            "low_idx": 14
        },
        {
            "high_idx": 0,
            "image_name": "000000056.png",
            "low_idx": 14
        },
        {
            "high_idx": 0,
            "image_name": "000000057.png",
            "low_idx": 15
        },
        {
            "high_idx": 0,
            "image_name": "000000058.png",
            "low_idx": 15
        },
        {
            "high_idx": 0,
            "image_name": "000000059.png",
            "low_idx": 15
        },
        {
            "high_idx": 0,
            "image_name": "000000060.png",
            "low_idx": 15
        },
        {
            "high_idx": 0,
            "image_name": "000000061.png",
            "low_idx": 15
        },
        {
            "high_idx": 0,
            "image_name": "000000062.png",
            "low_idx": 15
        },
        {
            "high_idx": 0,
            "image_name": "000000063.png",
            "low_idx": 15
        },
        {
            "high_idx": 0,
            "image_name": "000000064.png",
            "low_idx": 15
        },
        {
            "high_idx": 0,
            "image_name": "000000065.png",
            "low_idx": 15
        },
        {
            "high_idx": 0,
            "image_name": "000000066.png",
            "low_idx": 15
        },
        {
            "high_idx": 0,
            "image_name": "000000067.png",
            "low_idx": 15
        },
        {
            "high_idx": 1,
            "image_name": "000000068.png",
            "low_idx": 16
        },
        {
            "high_idx": 1,
            "image_name": "000000069.png",
            "low_idx": 16
        },
        {
            "high_idx": 1,
            "image_name": "000000070.png",
            "low_idx": 16
        },
        {
            "high_idx": 1,
            "image_name": "000000071.png",
            "low_idx": 16
        },
        {
            "high_idx": 1,
            "image_name": "000000072.png",
            "low_idx": 16
        },
        {
            "high_idx": 1,
            "image_name": "000000073.png",
            "low_idx": 16
        },
        {
            "high_idx": 1,
            "image_name": "000000074.png",
            "low_idx": 16
        },
        {
            "high_idx": 1,
            "image_name": "000000075.png",
            "low_idx": 16
        },
        {
            "high_idx": 1,
            "image_name": "000000076.png",
            "low_idx": 16
        },
        {
            "high_idx": 1,
            "image_name": "000000077.png",
            "low_idx": 16
        },
        {
            "high_idx": 1,
            "image_name": "000000078.png",
            "low_idx": 16
        },
        {
            "high_idx": 1,
            "image_name": "000000079.png",
            "low_idx": 16
        },
        {
            "high_idx": 1,
            "image_name": "000000080.png",
            "low_idx": 16
        },
        {
            "high_idx": 1,
            "image_name": "000000081.png",
            "low_idx": 16
        },
        {
            "high_idx": 1,
            "image_name": "000000082.png",
            "low_idx": 16
        },
        {
            "high_idx": 2,
            "image_name": "000000083.png",
            "low_idx": 17
        },
        {
            "high_idx": 2,
            "image_name": "000000084.png",
            "low_idx": 17
        },
        {
            "high_idx": 2,
            "image_name": "000000085.png",
            "low_idx": 17
        },
        {
            "high_idx": 2,
            "image_name": "000000086.png",
            "low_idx": 17
        },
        {
            "high_idx": 2,
            "image_name": "000000087.png",
            "low_idx": 17
        },
        {
            "high_idx": 2,
            "image_name": "000000088.png",
            "low_idx": 17
        },
        {
            "high_idx": 2,
            "image_name": "000000089.png",
            "low_idx": 17
        },
        {
            "high_idx": 2,
            "image_name": "000000090.png",
            "low_idx": 17
        },
        {
            "high_idx": 2,
            "image_name": "000000091.png",
            "low_idx": 17
        },
        {
            "high_idx": 2,
            "image_name": "000000092.png",
            "low_idx": 17
        },
        {
            "high_idx": 2,
            "image_name": "000000093.png",
            "low_idx": 17
        },
        {
            "high_idx": 2,
            "image_name": "000000094.png",
            "low_idx": 18
        },
        {
            "high_idx": 2,
            "image_name": "000000095.png",
            "low_idx": 18
        },
        {
            "high_idx": 2,
            "image_name": "000000096.png",
            "low_idx": 18
        },
        {
            "high_idx": 2,
            "image_name": "000000097.png",
            "low_idx": 18
        },
        {
            "high_idx": 2,
            "image_name": "000000098.png",
            "low_idx": 18
        },
        {
            "high_idx": 2,
            "image_name": "000000099.png",
            "low_idx": 18
        },
        {
            "high_idx": 2,
            "image_name": "000000100.png",
            "low_idx": 18
        },
        {
            "high_idx": 2,
            "image_name": "000000101.png",
            "low_idx": 18
        },
        {
            "high_idx": 2,
            "image_name": "000000102.png",
            "low_idx": 18
        },
        {
            "high_idx": 2,
            "image_name": "000000103.png",
            "low_idx": 18
        },
        {
            "high_idx": 2,
            "image_name": "000000104.png",
            "low_idx": 18
        },
        {
            "high_idx": 2,
            "image_name": "000000105.png",
            "low_idx": 19
        },
        {
            "high_idx": 2,
            "image_name": "000000106.png",
            "low_idx": 19
        },
        {
            "high_idx": 2,
            "image_name": "000000107.png",
            "low_idx": 20
        },
        {
            "high_idx": 2,
            "image_name": "000000108.png",
            "low_idx": 20
        },
        {
            "high_idx": 2,
            "image_name": "000000109.png",
            "low_idx": 21
        },
        {
            "high_idx": 2,
            "image_name": "000000110.png",
            "low_idx": 21
        },
        {
            "high_idx": 2,
            "image_name": "000000111.png",
            "low_idx": 22
        },
        {
            "high_idx": 2,
            "image_name": "000000112.png",
            "low_idx": 22
        },
        {
            "high_idx": 2,
            "image_name": "000000113.png",
            "low_idx": 23
        },
        {
            "high_idx": 2,
            "image_name": "000000114.png",
            "low_idx": 23
        },
        {
            "high_idx": 2,
            "image_name": "000000115.png",
            "low_idx": 24
        },
        {
            "high_idx": 2,
            "image_name": "000000116.png",
            "low_idx": 24
        },
        {
            "high_idx": 2,
            "image_name": "000000117.png",
            "low_idx": 25
        },
        {
            "high_idx": 2,
            "image_name": "000000118.png",
            "low_idx": 25
        },
        {
            "high_idx": 2,
            "image_name": "000000119.png",
            "low_idx": 26
        },
        {
            "high_idx": 2,
            "image_name": "000000120.png",
            "low_idx": 26
        },
        {
            "high_idx": 2,
            "image_name": "000000121.png",
            "low_idx": 27
        },
        {
            "high_idx": 2,
            "image_name": "000000122.png",
            "low_idx": 27
        },
        {
            "high_idx": 2,
            "image_name": "000000123.png",
            "low_idx": 28
        },
        {
            "high_idx": 2,
            "image_name": "000000124.png",
            "low_idx": 28
        },
        {
            "high_idx": 2,
            "image_name": "000000125.png",
            "low_idx": 29
        },
        {
            "high_idx": 2,
            "image_name": "000000126.png",
            "low_idx": 29
        },
        {
            "high_idx": 2,
            "image_name": "000000127.png",
            "low_idx": 30
        },
        {
            "high_idx": 2,
            "image_name": "000000128.png",
            "low_idx": 30
        },
        {
            "high_idx": 2,
            "image_name": "000000129.png",
            "low_idx": 30
        },
        {
            "high_idx": 2,
            "image_name": "000000130.png",
            "low_idx": 30
        },
        {
            "high_idx": 2,
            "image_name": "000000131.png",
            "low_idx": 30
        },
        {
            "high_idx": 2,
            "image_name": "000000132.png",
            "low_idx": 30
        },
        {
            "high_idx": 2,
            "image_name": "000000133.png",
            "low_idx": 30
        },
        {
            "high_idx": 2,
            "image_name": "000000134.png",
            "low_idx": 30
        },
        {
            "high_idx": 2,
            "image_name": "000000135.png",
            "low_idx": 30
        },
        {
            "high_idx": 2,
            "image_name": "000000136.png",
            "low_idx": 30
        },
        {
            "high_idx": 2,
            "image_name": "000000137.png",
            "low_idx": 30
        },
        {
            "high_idx": 2,
            "image_name": "000000138.png",
            "low_idx": 31
        },
        {
            "high_idx": 2,
            "image_name": "000000139.png",
            "low_idx": 31
        },
        {
            "high_idx": 2,
            "image_name": "000000140.png",
            "low_idx": 32
        },
        {
            "high_idx": 2,
            "image_name": "000000141.png",
            "low_idx": 32
        },
        {
            "high_idx": 2,
            "image_name": "000000142.png",
            "low_idx": 33
        },
        {
            "high_idx": 2,
            "image_name": "000000143.png",
            "low_idx": 33
        },
        {
            "high_idx": 2,
            "image_name": "000000144.png",
            "low_idx": 34
        },
        {
            "high_idx": 2,
            "image_name": "000000145.png",
            "low_idx": 34
        },
        {
            "high_idx": 2,
            "image_name": "000000146.png",
            "low_idx": 35
        },
        {
            "high_idx": 2,
            "image_name": "000000147.png",
            "low_idx": 35
        },
        {
            "high_idx": 2,
            "image_name": "000000148.png",
            "low_idx": 35
        },
        {
            "high_idx": 2,
            "image_name": "000000149.png",
            "low_idx": 35
        },
        {
            "high_idx": 2,
            "image_name": "000000150.png",
            "low_idx": 35
        },
        {
            "high_idx": 2,
            "image_name": "000000151.png",
            "low_idx": 35
        },
        {
            "high_idx": 2,
            "image_name": "000000152.png",
            "low_idx": 35
        },
        {
            "high_idx": 2,
            "image_name": "000000153.png",
            "low_idx": 35
        },
        {
            "high_idx": 2,
            "image_name": "000000154.png",
            "low_idx": 35
        },
        {
            "high_idx": 2,
            "image_name": "000000155.png",
            "low_idx": 35
        },
        {
            "high_idx": 2,
            "image_name": "000000156.png",
            "low_idx": 35
        },
        {
            "high_idx": 2,
            "image_name": "000000157.png",
            "low_idx": 36
        },
        {
            "high_idx": 2,
            "image_name": "000000158.png",
            "low_idx": 36
        },
        {
            "high_idx": 2,
            "image_name": "000000159.png",
            "low_idx": 36
        },
        {
            "high_idx": 2,
            "image_name": "000000160.png",
            "low_idx": 36
        },
        {
            "high_idx": 2,
            "image_name": "000000161.png",
            "low_idx": 36
        },
        {
            "high_idx": 2,
            "image_name": "000000162.png",
            "low_idx": 36
        },
        {
            "high_idx": 2,
            "image_name": "000000163.png",
            "low_idx": 36
        },
        {
            "high_idx": 2,
            "image_name": "000000164.png",
            "low_idx": 36
        },
        {
            "high_idx": 2,
            "image_name": "000000165.png",
            "low_idx": 36
        },
        {
            "high_idx": 2,
            "image_name": "000000166.png",
            "low_idx": 36
        },
        {
            "high_idx": 2,
            "image_name": "000000167.png",
            "low_idx": 36
        },
        {
            "high_idx": 3,
            "image_name": "000000168.png",
            "low_idx": 37
        },
        {
            "high_idx": 3,
            "image_name": "000000169.png",
            "low_idx": 37
        },
        {
            "high_idx": 3,
            "image_name": "000000170.png",
            "low_idx": 37
        },
        {
            "high_idx": 3,
            "image_name": "000000171.png",
            "low_idx": 37
        },
        {
            "high_idx": 3,
            "image_name": "000000172.png",
            "low_idx": 37
        },
        {
            "high_idx": 3,
            "image_name": "000000173.png",
            "low_idx": 37
        },
        {
            "high_idx": 3,
            "image_name": "000000174.png",
            "low_idx": 37
        },
        {
            "high_idx": 3,
            "image_name": "000000175.png",
            "low_idx": 37
        },
        {
            "high_idx": 3,
            "image_name": "000000176.png",
            "low_idx": 37
        },
        {
            "high_idx": 3,
            "image_name": "000000177.png",
            "low_idx": 37
        },
        {
            "high_idx": 3,
            "image_name": "000000178.png",
            "low_idx": 37
        },
        {
            "high_idx": 3,
            "image_name": "000000179.png",
            "low_idx": 37
        },
        {
            "high_idx": 3,
            "image_name": "000000180.png",
            "low_idx": 37
        },
        {
            "high_idx": 3,
            "image_name": "000000181.png",
            "low_idx": 37
        },
        {
            "high_idx": 3,
            "image_name": "000000182.png",
            "low_idx": 37
        }
    ],
    "pddl_params": {
        "mrecep_target": "",
        "object_sliced": false,
        "object_target": "PencilCase",
        "parent_target": "SideTable",
        "toggle_target": ""
    },
    "plan": {
        "high_pddl": [
            {
                "discrete_action": {
                    "action": "GotoLocation",
                    "args": [
                        "sofa"
                    ]
                },
                "high_idx": 0,
                "planner_action": {
                    "action": "GotoLocation",
                    "location": "loc|7|-3|2|60"
                }
            },
            {
                "discrete_action": {
                    "action": "PickupObject",
                    "args": [
                        "pencilcase"
                    ]
                },
                "high_idx": 1,
                "planner_action": {
                    "action": "PickupObject",
                    "forceVisible": true,
                    "objectId": "PencilCase|+01.69|+00.47|-01.45",
                    "receptacleObjectId": "Sofa|+01.60|+00.05|-02.18"
                }
            },
            {
                "discrete_action": {
                    "action": "GotoLocation",
                    "args": [
                        "sidetable"
                    ]
                },
                "high_idx": 2,
                "planner_action": {
                    "action": "GotoLocation",
                    "location": "loc|18|-7|3|30"
                }
            },
            {
                "discrete_action": {
                    "action": "PutObject",
                    "args": [
                        "pencilcase",
                        "sidetable"
                    ]
                },
                "high_idx": 3,
                "planner_action": {
                    "action": "PutObject",
                    "forceVisible": true,
                    "objectId": "PencilCase|+01.69|+00.47|-01.45",
                    "receptacleObjectId": "SideTable|+01.71|+00.00|-04.39"
                }
            }
        ],
        "low_actions": [
            {
                "api_action": {
                    "action": "LookDown"
                },
                "discrete_action": {
                    "action": "LookDown_15",
                    "args": {}
                },
                "high_idx": 0
            },
            {
                "api_action": {
                    "action": "RotateLeft",
                    "forceAction": true
                },
                "discrete_action": {
                    "action": "RotateLeft_90",
                    "args": {}
                },
                "high_idx": 0
            },
            {
                "api_action": {
                    "action": "MoveAhead",
                    "forceAction": true,
                    "moveMagnitude": 0.25
                },
                "discrete_action": {
                    "action": "MoveAhead_25",
                    "args": {}
                },
                "high_idx": 0
            },
            {
                "api_action": {
                    "action": "MoveAhead",
                    "forceAction": true,
                    "moveMagnitude": 0.25
                },
                "discrete_action": {
                    "action": "MoveAhead_25",
                    "args": {}
                },
                "high_idx": 0
            },
            {
                "api_action": {
                    "action": "MoveAhead",
                    "forceAction": true,
                    "moveMagnitude": 0.25
                },
                "discrete_action": {
                    "action": "MoveAhead_25",
                    "args": {}
                },
                "high_idx": 0
            },
            {
                "api_action": {
                    "action": "MoveAhead",
                    "forceAction": true,
                    "moveMagnitude": 0.25
                },
                "discrete_action": {
                    "action": "MoveAhead_25",
                    "args": {}
                },
                "high_idx": 0
            },
            {
                "api_action": {
                    "action": "MoveAhead",
                    "forceAction": true,
                    "moveMagnitude": 0.25
                },
                "discrete_action": {
                    "action": "MoveAhead_25",
                    "args": {}
                },
                "high_idx": 0
            },
            {
                "api_action": {
                    "action": "MoveAhead",
                    "forceAction": true,
                    "moveMagnitude": 0.25
                },
                "discrete_action": {
                    "action": "MoveAhead_25",
                    "args": {}
                },
                "high_idx": 0
            },
            {
                "api_action": {
                    "action": "MoveAhead",
                    "forceAction": true,
                    "moveMagnitude": 0.25
                },
                "discrete_action": {
                    "action": "MoveAhead_25",
                    "args": {}
                },
                "high_idx": 0
            },
            {
                "api_action": {
                    "action": "MoveAhead",
                    "forceAction": true,
                    "moveMagnitude": 0.25
                },
                "discrete_action": {
                    "action": "MoveAhead_25",
                    "args": {}
                },
                "high_idx": 0
            },
            {
                "api_action": {
                    "action": "MoveAhead",
                    "forceAction": true,
                    "moveMagnitude": 0.25
                },
                "discrete_action": {
                    "action": "MoveAhead_25",
                    "args": {}
                },
                "high_idx": 0
            },
            {
                "api_action": {
                    "action": "MoveAhead",
                    "forceAction": true,
                    "moveMagnitude": 0.25
                },
                "discrete_action": {
                    "action": "MoveAhead_25",
                    "args": {}
                },
                "high_idx": 0
            },
            {
                "api_action": {
                    "action": "RotateLeft",
                    "forceAction": true
                },
                "discrete_action": {
                    "action": "RotateLeft_90",
                    "args": {}
                },
                "high_idx": 0
            },
            {
                "api_action": {
                    "action": "MoveAhead",
                    "forceAction": true,
                    "moveMagnitude": 0.25
                },
                "discrete_action": {
                    "action": "MoveAhead_25",
                    "args": {}
                },
                "high_idx": 0
            },
            {
                "api_action": {
                    "action": "MoveAhead",
                    "forceAction": true,
                    "moveMagnitude": 0.25
                },
                "discrete_action": {
                    "action": "MoveAhead_25",
                    "args": {}
                },
                "high_idx": 0
            },
            {
                "api_action": {
                    "action": "LookDown",
                    "forceAction": true
                },
                "discrete_action": {
                    "action": "LookDown_15",
                    "args": {}
                },
                "high_idx": 0
            },
            {
                "api_action": {
                    "action": "PickupObject",
                    "objectId": "PencilCase|+01.69|+00.47|-01.45"
                },
                "discrete_action": {
                    "action": "PickupObject",
                    "args": {
                        "bbox": [
                            154,
                            132,
                            159,
                            156
                        ],
                        "mask": [
                            [
                                39756,
                                3
                            ],
                            [
                                40056,
                                4
                            ],
                            [
                                40355,
                                4
                            ],
                            [
                                40655,
                                4
                            ],
                            [
                                40954,
                                5
                            ],
                            [
                                41254,
                                5
                            ],
                            [
                                41554,
                                5
                            ],
                            [
                                41855,
                                4
                            ],
                            [
                                42155,
                                4
                            ],
                            [
                                42455,
                                4
                            ],
                            [
                                42755,
                                4
                            ],
                            [
                                43055,
                                4
                            ],
                            [
                                43355,
                                5
                            ],
                            [
                                43655,
                                5
                            ],
                            [
                                43955,
                                5
                            ],
                            [
                                44255,
                                5
                            ],
                            [
                                44555,
                                5
                            ],
                            [
                                44855,
                                5
                            ],
                            [
                                45155,
                                5
                            ],
                            [
                                45455,
                                5
                            ],
                            [
                                45755,
                                5
                            ],
                            [
                                46055,
                                5
                            ],
                            [
                                46355,
                                5
                            ],
                            [
                                46655,
                                5
                            ],
                            [
                                46955,
                                5
                            ]
                        ],
                        "point": [
                            156,
                            144
                        ]
                    }
                },
                "high_idx": 1
            },
            {
                "api_action": {
                    "action": "LookUp"
                },
                "discrete_action": {
                    "action": "LookUp_15",
                    "args": {}
                },
                "high_idx": 2
            },
            {
                "api_action": {
                    "action": "RotateLeft",
                    "forceAction": true
                },
                "discrete_action": {
                    "action": "RotateLeft_90",
                    "args": {}
                },
                "high_idx": 2
            },
            {
                "api_action": {
                    "action": "MoveAhead",
                    "forceAction": true,
                    "moveMagnitude": 0.25
                },
                "discrete_action": {
                    "action": "MoveAhead_25",
                    "args": {}
                },
                "high_idx": 2
            },
            {
                "api_action": {
                    "action": "MoveAhead",
                    "forceAction": true,
                    "moveMagnitude": 0.25
                },
                "discrete_action": {
                    "action": "MoveAhead_25",
                    "args": {}
                },
                "high_idx": 2
            },
            {
                "api_action": {
                    "action": "MoveAhead",
                    "forceAction": true,
                    "moveMagnitude": 0.25
                },
                "discrete_action": {
                    "action": "MoveAhead_25",
                    "args": {}
                },
                "high_idx": 2
            },
            {
                "api_action": {
                    "action": "MoveAhead",
                    "forceAction": true,
                    "moveMagnitude": 0.25
                },
                "discrete_action": {
                    "action": "MoveAhead_25",
                    "args": {}
                },
                "high_idx": 2
            },
            {
                "api_action": {
                    "action": "MoveAhead",
                    "forceAction": true,
                    "moveMagnitude": 0.25
                },
                "discrete_action": {
                    "action": "MoveAhead_25",
                    "args": {}
                },
                "high_idx": 2
            },
            {
                "api_action": {
                    "action": "MoveAhead",
                    "forceAction": true,
                    "moveMagnitude": 0.25
                },
                "discrete_action": {
                    "action": "MoveAhead_25",
                    "args": {}
                },
                "high_idx": 2
            },
            {
                "api_action": {
                    "action": "MoveAhead",
                    "forceAction": true,
                    "moveMagnitude": 0.25
                },
                "discrete_action": {
                    "action": "MoveAhead_25",
                    "args": {}
                },
                "high_idx": 2
            },
            {
                "api_action": {
                    "action": "MoveAhead",
                    "forceAction": true,
                    "moveMagnitude": 0.25
                },
                "discrete_action": {
                    "action": "MoveAhead_25",
                    "args": {}
                },
                "high_idx": 2
            },
            {
                "api_action": {
                    "action": "MoveAhead",
                    "forceAction": true,
                    "moveMagnitude": 0.25
                },
                "discrete_action": {
                    "action": "MoveAhead_25",
                    "args": {}
                },
                "high_idx": 2
            },
            {
                "api_action": {
                    "action": "MoveAhead",
                    "forceAction": true,
                    "moveMagnitude": 0.25
                },
                "discrete_action": {
                    "action": "MoveAhead_25",
                    "args": {}
                },
                "high_idx": 2
            },
            {
                "api_action": {
                    "action": "MoveAhead",
                    "forceAction": true,
                    "moveMagnitude": 0.25
                },
                "discrete_action": {
                    "action": "MoveAhead_25",
                    "args": {}
                },
                "high_idx": 2
            },
            {
                "api_action": {
                    "action": "RotateRight",
                    "forceAction": true
                },
                "discrete_action": {
                    "action": "RotateRight_90",
                    "args": {}
                },
                "high_idx": 2
            },
            {
                "api_action": {
                    "action": "MoveAhead",
                    "forceAction": true,
                    "moveMagnitude": 0.25
                },
                "discrete_action": {
                    "action": "MoveAhead_25",
                    "args": {}
                },
                "high_idx": 2
            },
            {
                "api_action": {
                    "action": "MoveAhead",
                    "forceAction": true,
                    "moveMagnitude": 0.25
                },
                "discrete_action": {
                    "action": "MoveAhead_25",
                    "args": {}
                },
                "high_idx": 2
            },
            {
                "api_action": {
                    "action": "MoveAhead",
                    "forceAction": true,
                    "moveMagnitude": 0.25
                },
                "discrete_action": {
                    "action": "MoveAhead_25",
                    "args": {}
                },
                "high_idx": 2
            },
            {
                "api_action": {
                    "action": "MoveAhead",
                    "forceAction": true,
                    "moveMagnitude": 0.25
                },
                "discrete_action": {
                    "action": "MoveAhead_25",
                    "args": {}
                },
                "high_idx": 2
            },
            {
                "api_action": {
                    "action": "RotateRight",
                    "forceAction": true
                },
                "discrete_action": {
                    "action": "RotateRight_90",
                    "args": {}
                },
                "high_idx": 2
            },
            {
                "api_action": {
                    "action": "LookUp",
                    "forceAction": true
                },
                "discrete_action": {
                    "action": "LookUp_15",
                    "args": {}
                },
                "high_idx": 2
            },
            {
                "api_action": {
                    "action": "PutObject",
                    "forceAction": true,
                    "objectId": "SideTable|+01.71|+00.00|-04.39",
                    "placeStationary": true
                },
                "discrete_action": {
                    "action": "PutObject",
                    "args": {
                        "bbox": [
                            45,
                            165,
                            153,
                            215
                        ],
                        "mask": [
                            [
                                49571,
                                82
                            ],
                            [
                                49870,
                                83
                            ],
                            [
                                50169,
                                84
                            ],
                            [
                                50469,
                                84
                            ],
                            [
                                50768,
                                85
                            ],
                            [
                                51067,
                                28
                            ],
                            [
                                51102,
                                51
                            ],
                            [
                                51366,
                                28
                            ],
                            [
                                51402,
                                16
                            ],
                            [
                                51421,
                                32
                            ],
                            [
                                51666,
                                28
                            ],
                            [
                                51699,
                                19
                            ],
                            [
                                51721,
                                11
                            ],
                            [
                                51744,
                                9
                            ],
                            [
                                51965,
                                28
                            ],
                            [
                                51998,
                                20
                            ],
                            [
                                52022,
                                10
                            ],
                            [
                                52044,
                                9
                            ],
                            [
                                52264,
                                29
                            ],
                            [
                                52299,
                                18
                            ],
                            [
                                52322,
                                10
                            ],
                            [
                                52344,
                                9
                            ],
                            [
                                52563,
                                30
                            ],
                            [
                                52599,
                                18
                            ],
                            [
                                52623,
                                9
                            ],
                            [
                                52644,
                                9
                            ],
                            [
                                52862,
                                36
                            ],
                            [
                                52899,
                                18
                            ],
                            [
                                52923,
                                8
                            ],
                            [
                                52944,
                                9
                            ],
                            [
                                53162,
                                15
                            ],
                            [
                                53186,
                                31
                            ],
                            [
                                53223,
                                30
                            ],
                            [
                                53461,
                                16
                            ],
                            [
                                53486,
                                31
                            ],
                            [
                                53523,
                                31
                            ],
                            [
                                53760,
                                17
                            ],
                            [
                                53785,
                                33
                            ],
                            [
                                53823,
                                31
                            ],
                            [
                                54059,
                                17
                            ],
                            [
                                54085,
                                3
                            ],
                            [
                                54091,
                                27
                            ],
                            [
                                54123,
                                31
                            ],
                            [
                                54359,
                                17
                            ],
                            [
                                54385,
                                33
                            ],
                            [
                                54423,
                                31
                            ],
                            [
                                54658,
                                18
                            ],
                            [
                                54684,
                                34
                            ],
                            [
                                54723,
                                31
                            ],
                            [
                                54957,
                                19
                            ],
                            [
                                54984,
                                20
                            ],
                            [
                                55016,
                                2
                            ],
                            [
                                55024,
                                30
                            ],
                            [
                                55256,
                                20
                            ],
                            [
                                55283,
                                5
                            ],
                            [
                                55317,
                                1
                            ],
                            [
                                55323,
                                31
                            ],
                            [
                                55556,
                                21
                            ],
                            [
                                55583,
                                5
                            ],
                            [
                                55595,
                                5
                            ],
                            [
                                55611,
                                8
                            ],
                            [
                                55623,
                                15
                            ],
                            [
                                55642,
                                12
                            ],
                            [
                                55855,
                                22
                            ],
                            [
                                55882,
                                55
                            ],
                            [
                                55942,
                                12
                            ],
                            [
                                56154,
                                24
                            ],
                            [
                                56181,
                                56
                            ],
                            [
                                56242,
                                12
                            ],
                            [
                                56453,
                                25
                            ],
                            [
                                56480,
                                57
                            ],
                            [
                                56542,
                                12
                            ],
                            [
                                56752,
                                26
                            ],
                            [
                                56779,
                                58
                            ],
                            [
                                56842,
                                12
                            ],
                            [
                                57052,
                                85
                            ],
                            [
                                57142,
                                12
                            ],
                            [
                                57351,
                                103
                            ],
                            [
                                57650,
                                104
                            ],
                            [
                                57949,
                                105
                            ],
                            [
                                58249,
                                105
                            ],
                            [
                                58548,
                                106
                            ],
                            [
                                58847,
                                107
                            ],
                            [
                                59146,
                                108
                            ],
                            [
                                59445,
                                109
                            ],
                            [
                                59745,
                                109
                            ],
                            [
                                60045,
                                109
                            ],
                            [
                                60345,
                                69
                            ],
                            [
                                60419,
                                35
                            ],
                            [
                                60646,
                                66
                            ],
                            [
                                60714,
                                4
                            ],
                            [
                                60720,
                                34
                            ],
                            [
                                60946,
                                66
                            ],
                            [
                                61013,
                                6
                            ],
                            [
                                61021,
                                33
                            ],
                            [
                                61247,
                                64
                            ],
                            [
                                61314,
                                6
                            ],
                            [
                                61321,
                                33
                            ],
                            [
                                61547,
                                64
                            ],
                            [
                                61615,
                                5
                            ],
                            [
                                61621,
                                33
                            ],
                            [
                                61848,
                                58
                            ],
                            [
                                62148,
                                57
                            ],
                            [
                                62449,
                                56
                            ],
                            [
                                62749,
                                56
                            ],
                            [
                                63050,
                                55
                            ],
                            [
                                63350,
                                54
                            ],
                            [
                                63651,
                                54
                            ],
                            [
                                63951,
                                54
                            ],
                            [
                                64252,
                                8
                            ],
                            [
                                64262,
                                44
                            ],
                            [
                                64552,
                                7
                            ],
                            [
                                64562,
                                6
                            ]
                        ],
                        "point": [
                            99,
                            190
                        ]
                    }
                },
                "high_idx": 3
            }
        ]
    },
    "scene": {
        "dirty_and_empty": false,
        "floor_plan": "FloorPlan298",
        "init_action": {
            "action": "TeleportFull",
            "horizon": 30,
            "position": {
                "x": 4.25,
                "y": 0.9019261598587036,
                "z": -0.25
            },
            "rotation": {
                "x": 0,
                "y": 0,
                "z": 0
            },
            "standing": true
        },
        "object_poses": [
            {
                "objectName": "Armchair_220_Master (1)",
                "position": {
                    "x": 1.4858386516571045,
                    "y": 0.025516927242279053,
                    "z": 3.8709728717803955
                },
                "rotation": {
                    "x": 0.04908089339733124,
                    "y": 179.8050537109375,
                    "z": 2.720830202102661
                }
            },
            {
                "objectName": "Armchair_220_Master",
                "position": {
                    "x": 0.7435081005096436,
                    "y": 0.04954516887664795,
                    "z": 3.8633368015289307
                },
                "rotation": {
                    "x": 0.8822981119155884,
                    "y": 181.22003173828125,
                    "z": 359.3372802734375
                }
            },
            {
                "objectName": "Banana",
                "position": {
                    "x": 0.7929463982582092,
                    "y": 0.47535163164138794,
                    "z": 3.7043700218200684
                },
                "rotation": {
                    "x": 270.5478515625,
                    "y": 216.94308471679688,
                    "z": 152.9930419921875
                }
            },
            {
                "objectName": "Bed_4",
                "position": {
                    "x": 6.560000419616699,
                    "y": 0.0010027885437011719,
                    "z": 1.7000000476837158
                },
                "rotation": {
                    "x": -0.0,
                    "y": 270.0,
                    "z": 0.0
                }
            },
            {
                "objectName": "Book_16",
                "position": {
                    "x": 6.1044602394104,
                    "y": 0.6783127188682556,
                    "z": 3.874239206314087
                },
                "rotation": {
                    "x": 353.0145568847656,
                    "y": 358.9708557128906,
                    "z": 359.35955810546875
                }
            },
            {
                "objectName": "Bottle_HF",
                "position": {
                    "x": 3.22367262840271,
                    "y": 0.3865208625793457,
                    "z": -2.079664945602417
                },
                "rotation": {
                    "x": 0.002537149004638195,
                    "y": 0.00011251118849031627,
                    "z": 1.4137905054667499e-05
                }
            },
            {
                "objectName": "Calculrator",
                "position": {
                    "x": 3.0489015579223633,
                    "y": 0.38661012053489685,
                    "z": -1.902714729309082
                },
                "rotation": {
                    "x": -0.0001825527288019657,
                    "y": 0.0002637405414134264,
                    "z": -0.0005224405904300511
                }
            },
            {
                "objectName": "CannedFood",
                "position": {
                    "x": 1.0562993288040161,
                    "y": 1.036302924156189,
                    "z": 1.3327008485794067
                },
                "rotation": {
                    "x": 270.46856689453125,
                    "y": 31.02834701538086,
                    "z": 328.8997497558594
                }
            },
            {
                "objectName": "Chair_313_Master",
                "position": {
                    "x": 5.5199995040893555,
                    "y": -0.017965614795684814,
                    "z": 3.407278299331665
                },
                "rotation": {
                    "x": 0.00025707425083965063,
                    "y": -0.00012102256005164236,
                    "z": -6.70281660859473e-05
                }
            },
            {
                "objectName": "GameStick",
                "position": {
                    "x": 3.0369791984558105,
                    "y": 0.3879684805870056,
                    "z": -2.40153169631958
                },
                "rotation": {
                    "x": -0.0021296218037605286,
                    "y": 0.0014043847331777215,
                    "z": 359.9942321777344
                }
            },
            {
                "objectName": "CreditCard_3",
                "position": {
                    "x": 3.2818164825439453,
                    "y": 0.3870058059692383,
                    "z": -1.8652830123901367
                },
                "rotation": {
                    "x": -0.0005714125582017004,
                    "y": 0.005303533747792244,
                    "z": -0.005419366993010044
                }
            },
            {
                "objectName": "Desk_320_1_Master",
                "position": {
                    "x": 5.590145111083984,
                    "y": 0.0039044618606567383,
                    "z": 4.018993377685547
                },
                "rotation": {
                    "x": 7.005553245544434,
                    "y": 176.96803283691406,
                    "z": 0.38981324434280396
                }
            },
            {
                "objectName": "Eggplant",
                "position": {
                    "x": 1.0088810920715332,
                    "y": 0.7459192276000977,
                    "z": 1.2038956880569458
                },
                "rotation": {
                    "x": 13.962149620056152,
                    "y": 269.66387939453125,
                    "z": 83.88091278076172
                }
            },
            {
                "objectName": "Floor_Lamp_10",
                "position": {
                    "x": 0.30550631880760193,
                    "y": 0.007871389389038086,
                    "z": 3.2081656455993652
                },
                "rotation": {
                    "x": 359.97064208984375,
                    "y": 0.11537957191467285,
                    "z": 359.7516174316406
                }
            },
            {
                "objectName": "Knife_5",
                "position": {
                    "x": 3.237907886505127,
                    "y": 0.3937460780143738,
                    "z": -2.325664758682251
                },
                "rotation": {
                    "x": 0.006992192938923836,
                    "y": 354.5953063964844,
                    "z": 89.94451141357422
                }
            },
            {
                "objectName": "Mango",
                "position": {
                    "x": 1.8287259340286255,
                    "y": 0.4686037302017212,
                    "z": -2.1313066482543945
                },
                "rotation": {
                    "x": 7.6281962394714355,
                    "y": 332.3720397949219,
                    "z": 232.55194091796875
                }
            },
            {
                "objectName": "Pencil_6",
                "position": {
                    "x": 5.955138206481934,
                    "y": 0.684299647808075,
                    "z": 3.866062879562378
                },
                "rotation": {
                    "x": 352.974609375,
                    "y": 356.9847412109375,
                    "z": 313.51885986328125
                }
            },
            {
                "objectName": "PencilCase",
                "position": {
                    "x": 1.6857539415359497,
                    "y": 0.46704012155532837,
                    "z": -1.4524142742156982
                },
                "rotation": {
                    "x": 358.51971435546875,
                    "y": 269.97723388671875,
                    "z": 357.8232727050781
                }
            },
            {
                "objectName": "Plate_2",
                "position": {
                    "x": 5.604888916015625,
                    "y": 0.6839452981948853,
                    "z": 3.847024440765381
                },
                "rotation": {
                    "x": 352.9864807128906,
                    "y": 357.43951416015625,
                    "z": 359.52056884765625
                }
            },
            {
                "objectName": "ShelvingUnit_f69c6e02 (3)",
                "position": {
                    "x": 0.8884792327880859,
                    "y": 0.027381181716918945,
                    "z": 1.1382343769073486
                },
                "rotation": {
                    "x": 0.7620232701301575,
                    "y": 359.8947448730469,
                    "z": 359.72723388671875
                }
            },
            {
                "objectName": "Side_Table",
                "position": {
                    "x": 1.7089941501617432,
                    "y": 0.003101944923400879,
                    "z": -4.390002250671387
                },
                "rotation": {
                    "x": 9.707472781883553e-05,
                    "y": 90.00018310546875,
                    "z": -6.653039599768817e-05
                }
            },
            {
                "objectName": "Sofa_227_Master",
                "position": {
                    "x": 1.6009109020233154,
                    "y": 0.05172163248062134,
                    "z": -2.1780283451080322
                },
                "rotation": {
                    "x": 1.8804612159729004,
                    "y": 90.03654479980469,
                    "z": 0.00014735531294718385
                }
            },
            {
                "objectName": "Strawberry",
                "position": {
                    "x": 1.5178759098052979,
                    "y": 0.4166008532047272,
                    "z": 3.8674378395080566
                },
                "rotation": {
                    "x": 16.485008239746094,
                    "y": 32.524085998535156,
                    "z": 262.4100646972656
                }
            },
            {
                "objectName": "Tambourine",
                "position": {
                    "x": 2.215980291366577,
                    "y": 0.10539443045854568,
                    "z": -2.462111711502075
                },
                "rotation": {
                    "x": 64.22784423828125,
                    "y": 75.90052032470703,
                    "z": 271.6934509277344
                }
            },
            {
                "objectName": "Watermelon",
                "position": {
                    "x": 3.1953179836273193,
                    "y": 0.4006931781768799,
                    "z": -2.521862030029297
                },
                "rotation": {
                    "x": 7.9014763832092285,
                    "y": 0.03689460828900337,
                    "z": 0.29411572217941284
                }
            }
        ],
        "object_toggles": [],
        "random_seed": 2148457213,
        "scene_num": 298
    },
    "task_id": "trial_T20230703_162850_722373",
    "task_type": "pick_and_place_simple",
    "turk_annotations": {
        "anns": [
            {
                "assignment_id": "3DY4FPOOAHANZLC2N80UNDD1UWARVU",
                "high_descs": [
                    "Turn left and take few steps and turn left to reach the sofa",
                    "Take a pencil case from the sofa",
                    "Turn left and take few steps and again take a right turn and take immediate right to reach the side table",
                    "Put the pencil case on the left bottom corner side table"
                ],
                "task_desc": "Put the pencil case on the side table",
                "vote1": [
                    1,
                    1
                ],
                "vote2": []
            },
            {
                "assignment_id": "3TVRFO09G0140CMKI34GPM1N4FWLX4",
                "high_descs": [
                    "Turn left to reach the sofa.",
                    "Pick up the pencil case from the sofa.",
                    "Turn left to reach the side table.",
                    "Put the pencil case on the side table."
                ],
                "task_desc": "Put the pencil case on the side table.",
                "vote1": [
                    1,
                    1
                ],
                "vote2": []
            },
            {
                "assignment_id": "3TE22NPXPRYH42RPS03U6U2EPY044J",
                "high_descs": [
                    "Turn around turn right go straight to the sofa set \n",
                    "take on the pencil case ",
                    "Turn around turn right go straight to the side table\n",
                    "Put the pencil case in the side table\n"
                ],
                "task_desc": "Put the pencil case in the side table",
                "vote1": [
                    1,
                    1
                ],
                "vote2": []
            }
        ]
    }
}